{
  "display": {
    "icon": {
      "item": "minecraft:diamond"
    },
    "title": {
      "translate": "%1$s%3427655$s",
      "with": [
        "It's real!",
        {
          "translate": "advancement.bprmode4.overworld.obtain.diamond.title"
        }
      ]
    },
    "description": {
      "translate": "%1$s%3427655$s",
      "with": [
        "Disassemble diamond armor or tools for diamonds",
        {
          "translate": "advancement.bprmode4.overworld.obtain.diamond.description"
        }
      ],
      "color": "gray"
    },
    "frame": "task",
    "show_toast": true,
    "announce_to_chat": false,
    "hidden": false
  },
  "parent": "gm4:disassemblers",
  "criteria": {
    "diamond": {
      "trigger": "minecraft:inventory_changed",
      "conditions": {
        "items": [
          {
            "items": [
              "minecraft:diamond"
            ]
          }
        ]
      }
    }
  }
}
